Workbook

Sheet Executive Dashboard
A1: VORTEX ENTERPRISE GATEWAY - QA TEST EXECUTION DASHBOARD
A3: Automated Metrics Rollup & Quality Sign-Off Tracker | Generated for Manual QA Team
A5: Application Name: | B5: Vortex Payment Gateway & Conference Portal | D5: Test Execution Window: | E5: Release Candidate v2.4
A6: Target Environment: | B6: http://localhost:8080/vortex | D6: Lead QA Tester: | E6: Assigned QA Engineer
A7: Database Engine: | B7: MySQL 8.0 (payvortex) | D7: Server Environment: | E7: PHP 8.2 Built-in Server / Apache
A8: Admin URL: | B8: http://localhost:8080/vortex/admin/login.php | D8: Admin Credentials: | E8: admin / admin@123 (Super Admin)
A9: Merchant Portal URL: | B9: http://localhost:8080/vortex/portal/login.php | D9: Public Registration URL: | E9: http://localhost:8080/registration.html
A11: TEST EXECUTION PROGRESS SUMMARY (DYNAMIC FORMULAS)
A12: Total Test Cases | B12: Passed | C12: Failed | D12: Blocked | E12: Not Run | F12: Pass Rate (%)
A13: =COUNTA('Manual Test Cases'!A5:A100) | B13: =COUNTIF('Manual Test Cases'!I5:I100, "Pass") | C13: =COUNTIF('Manual Test Cases'!I5:I100, "Fail") | D13: =COUNTIF('Manual Test Cases'!I5:I100, "Blocked") | E13: =COUNTIF('Manual Test Cases'!I5:I100, "Not Run") | F13: =IF(A13>0, B13/A13, 0)
A16: TEST EXECUTION PROGRESS BY FEATURE MODULE
A17: Module Name | B17: Total | C17: Passed | D17: Failed | E17: Blocked | F17: Not Run | G17: Completion %
A18: Admin Authentication | B18: =COUNTIF('Manual Test Cases'!:00, A18) | C18: =COUNTIFS('Manual Test Cases'!:00, A18, 'Manual Test Cases'!:00, "Pass") | D18: =COUNTIFS('Manual Test Cases'!:00, A18, 'Manual Test Cases'!:00, "Fail") | E18: =COUNTIFS('Manual Test Cases'!:00, A18, 'Manual Test Cases'!:00, "Blocked") | F18: =COUNTIFS('Manual Test Cases'!:00, A18, 'Manual Test Cases'!:00, "Not Run") | G18: =IF(B18>0, (C18+D18+E18)/B18, 0)
A19: RBAC & Permissions | B19: =COUNTIF('Manual Test Cases'!:00, A19) | C19: =COUNTIFS('Manual Test Cases'!:00, A19, 'Manual Test Cases'!:00, "Pass") | D19: =COUNTIFS('Manual Test Cases'!:00, A19, 'Manual Test Cases'!:00, "Fail") | E19: =COUNTIFS('Manual Test Cases'!:00, A19, 'Manual Test Cases'!:00, "Blocked") | F19: =COUNTIFS('Manual Test Cases'!:00, A19, 'Manual Test Cases'!:00, "Not Run") | G19: =IF(B19>0, (C19+D19+E19)/B19, 0)
A20: Google Dark Mode | B20: =COUNTIF('Manual Test Cases'!:00, A20) | C20: =COUNTIFS('Manual Test Cases'!:00, A20, 'Manual Test Cases'!:00, "Pass") | D20: =COUNTIFS('Manual Test Cases'!:00, A20, 'Manual Test Cases'!:00, "Fail") | E20: =COUNTIFS('Manual Test Cases'!:00, A20, 'Manual Test Cases'!:00, "Blocked") | F20: =COUNTIFS('Manual Test Cases'!:00, A20, 'Manual Test Cases'!:00, "Not Run") | G20: =IF(B20>0, (C20+D20+E20)/B20, 0)
A21: Notification Center | B21: =COUNTIF('Manual Test Cases'!:00, A21) | C21: =COUNTIFS('Manual Test Cases'!:00, A21, 'Manual Test Cases'!:00, "Pass") | D21: =COUNTIFS('Manual Test Cases'!:00, A21, 'Manual Test Cases'!:00, "Fail") | E21: =COUNTIFS('Manual Test Cases'!:00, A21, 'Manual Test Cases'!:00, "Blocked") | F21: =COUNTIFS('Manual Test Cases'!:00, A21, 'Manual Test Cases'!:00, "Not Run") | G21: =IF(B21>0, (C21+D21+E21)/B21, 0)
A22: Global Search | B22: =COUNTIF('Manual Test Cases'!:00, A22) | C22: =COUNTIFS('Manual Test Cases'!:00, A22, 'Manual Test Cases'!:00, "Pass") | D22: =COUNTIFS('Manual Test Cases'!:00, A22, 'Manual Test Cases'!:00, "Fail") | E22: =COUNTIFS('Manual Test Cases'!:00, A22, 'Manual Test Cases'!:00, "Blocked") | F22: =COUNTIFS('Manual Test Cases'!:00, A22, 'Manual Test Cases'!:00, "Not Run") | G22: =IF(B22>0, (C22+D22+E22)/B22, 0)
A23: Client Onboarding | B23: =COUNTIF('Manual Test Cases'!:00, A23) | C23: =COUNTIFS('Manual Test Cases'!:00, A23, 'Manual Test Cases'!:00, "Pass") | D23: =COUNTIFS('Manual Test Cases'!:00, A23, 'Manual Test Cases'!:00, "Fail") | E23: =COUNTIFS('Manual Test Cases'!:00, A23, 'Manual Test Cases'!:00, "Blocked") | F23: =COUNTIFS('Manual Test Cases'!:00, A23, 'Manual Test Cases'!:00, "Not Run") | G23: =IF(B23>0, (C23+D23+E23)/B23, 0)
A24: Transactions & Refunds | B24: =COUNTIF('Manual Test Cases'!:00, A24) | C24: =COUNTIFS('Manual Test Cases'!:00, A24, 'Manual Test Cases'!:00, "Pass") | D24: =COUNTIFS('Manual Test Cases'!:00, A24, 'Manual Test Cases'!:00, "Fail") | E24: =COUNTIFS('Manual Test Cases'!:00, A24, 'Manual Test Cases'!:00, "Blocked") | F24: =COUNTIFS('Manual Test Cases'!:00, A24, 'Manual Test Cases'!:00, "Not Run") | G24: =IF(B24>0, (C24+D24+E24)/B24, 0)
A25: Merchant Portal | B25: =COUNTIF('Manual Test Cases'!:00, A25) | C25: =COUNTIFS('Manual Test Cases'!:00, A25, 'Manual Test Cases'!:00, "Pass") | D25: =COUNTIFS('Manual Test Cases'!:00, A25, 'Manual Test Cases'!:00, "Fail") | E25: =COUNTIFS('Manual Test Cases'!:00, A25, 'Manual Test Cases'!:00, "Blocked") | F25: =COUNTIFS('Manual Test Cases'!:00, A25, 'Manual Test Cases'!:00, "Not Run") | G25: =IF(B25>0, (C25+D25+E25)/B25, 0)
A26: Audit Trail | B26: =COUNTIF('Manual Test Cases'!:00, A26) | C26: =COUNTIFS('Manual Test Cases'!:00, A26, 'Manual Test Cases'!:00, "Pass") | D26: =COUNTIFS('Manual Test Cases'!:00, A26, 'Manual Test Cases'!:00, "Fail") | E26: =COUNTIFS('Manual Test Cases'!:00, A26, 'Manual Test Cases'!:00, "Blocked") | F26: =COUNTIFS('Manual Test Cases'!:00, A26, 'Manual Test Cases'!:00, "Not Run") | G26: =IF(B26>0, (C26+D26+E26)/B26, 0)
A27: Conference Registration | B27: =COUNTIF('Manual Test Cases'!:00, A27) | C27: =COUNTIFS('Manual Test Cases'!:00, A27, 'Manual Test Cases'!:00, "Pass") | D27: =COUNTIFS('Manual Test Cases'!:00, A27, 'Manual Test Cases'!:00, "Fail") | E27: =COUNTIFS('Manual Test Cases'!:00, A27, 'Manual Test Cases'!:00, "Blocked") | F27: =COUNTIFS('Manual Test Cases'!:00, A27, 'Manual Test Cases'!:00, "Not Run") | G27: =IF(B27>0, (C27+D27+E27)/B27, 0)
A28: Events Management | B28: =COUNTIF('Manual Test Cases'!:00, A28) | C28: =COUNTIFS('Manual Test Cases'!:00, A28, 'Manual Test Cases'!:00, "Pass") | D28: =COUNTIFS('Manual Test Cases'!:00, A28, 'Manual Test Cases'!:00, "Fail") | E28: =COUNTIFS('Manual Test Cases'!:00, A28, 'Manual Test Cases'!:00, "Blocked") | F28: =COUNTIFS('Manual Test Cases'!:00, A28, 'Manual Test Cases'!:00, "Not Run") | G28: =IF(B28>0, (C28+D28+E28)/B28, 0)
A29: Webhook Retry Queue | B29: =COUNTIF('Manual Test Cases'!:50, A29) | C29: =COUNTIFS('Manual Test Cases'!:50, A29, 'Manual Test Cases'!:50, "Pass") | D29: =COUNTIFS('Manual Test Cases'!:50, A29, 'Manual Test Cases'!:50, "Fail") | E29: =COUNTIFS('Manual Test Cases'!:50, A29, 'Manual Test Cases'!:50, "Blocked") | F29: =COUNTIFS('Manual Test Cases'!:50, A29, 'Manual Test Cases'!:50, "Not Run") | G29: =IF(B29>0, (C29+D29+E29)/B29, 0)
A31: QA TESTER OPERATING INSTRUCTIONS & DEFECT SEVERITY GUIDELINES
A32: Step 1: Test Execution | B32: Mark execution status for each test case in the 'Manual Test Cases' tab as 'Pass', 'Fail', or 'Blocked' using the dropdown.
A33: Step 2: Defect Logging | B33: For any test case marked 'Fail', log the complete issue under the 'Defect Log' sheet and link the Test ID (e.g. TC-AUTH-02).
A34: Step 3: Severity: Blocker | B34: System crash, database corruption, security bypass, or complete inability to process payments / login.
A35: Step 4: Severity: Critical | B35: Core feature failure without workaround (e.g. refund fails, search returns blank, webhook signature rejects valid ping).
A36: Step 5: Severity: Major | B36: Significant feature defect with indirect workaround (e.g. filter fails under specific date format, theme toggle lag).
A37: Step 6: Severity: Minor | B37: Visual layout inconsistency, cosmetic border issue, missing tooltip, or spelling discrepancy.

Sheet Manual Test Cases
A1: VORTEX PAYMENT GATEWAY & PORTAL - COMPREHENSIVE MANUAL TEST CASES
A3: Total Scenarios: 79 | Target Environment: http://localhost:8080/vortex | Role Coverage: Super Admin, Ops, Finance, Auditor, Merchant
A4: Test ID | B4: Module / Area | C4: Test Scenario / Title | D4: Priority | E4: Pre-conditions | F4: Step-by-Step Test Steps | G4: Test Data / Input Values | H4: Expected Result | I4: Status | J4: Actual Result / Findings | K4: Bug / Defect ID | L4: Tester Notes
A5: TC-AUTH-01 | B5: Admin Authentication | C5: Admin Login with valid credentials | D5: Critical | E5: Admin user exists in database (`admin`). Browser at /vortex/admin/login.php. | F5: 1. Open http://localhost:8080/vortex/admin/login.php in browser. 2. Enter Username: 'admin'. 3. Enter Password: 'admin@123'. 4. Click 'Sign In' button. | G5: Username: admin Password: admin@123 | H5: Login succeeds without delay. Session regenerated. User is redirected to /vortex/admin/dashboard.php. Topbar displays admin avatar, full name ('Vortex Administrator') and role badge. | I5: Not Run
A6: TC-AUTH-02 | B6: Admin Authentication | C6: Admin Login with incorrect password (Brute-Force deterrence) | D6: High | E6: Browser at /vortex/admin/login.php. | F6: 1. Open login page. 2. Enter Username: 'admin'. 3. Enter Password: 'wrongpassword999'. 4. Click 'Sign In' button. | G6: Username: admin Password: wrongpassword999 | H6: Login is rejected after ~1-second timing-safe delay. Error banner appears: 'Invalid username or password.'. User stays on login page. | I6: Not Run
A7: TC-AUTH-03 | B7: Admin Authentication | C7: Empty credentials submission validation | D7: Medium | E7: Browser at /vortex/admin/login.php. | F7: 1. Leave Username and Password inputs blank. 2. Click 'Sign In' button (bypass HTML5 required if needed). | G7: Username: '' Password: '' | H7: Validation blocks submission or displays error: 'Username and password are required.'. No session is created. | I7: Not Run
A8: TC-AUTH-04 | B8: Admin Authentication | C8: Session persistence & auto-redirect of logged-in admin | D8: Medium | E8: Admin is already signed in. | F8: 1. While signed in, navigate directly to http://localhost:8080/vortex/admin/login.php. | G8: Active session: vortex_admin_id=1 | H8: System recognizes existing active session and immediately redirects back to dashboard.php without displaying the login form. | I8: Not Run
A9: TC-AUTH-05 | B9: Admin Authentication | C9: Unauthenticated guard on protected admin routes | D9: Critical | E9: Browser in Incognito / no active session. | F9: 1. Directly open http://localhost:8080/vortex/admin/dashboard.php. 2. Directly open http://localhost:8080/vortex/admin/payments/list_payments.php. 3. Directly open http://localhost:8080/vortex/admin/notifications.php. | G9: HTTP GET without cookies | H9: All requests are intercepted by Auth Guard (RBAC/header) and redirected (HTTP 302) to /vortex/admin/login.php. No sensitive dashboard data is leaked. | I9: Not Run
A10: TC-AUTH-06 | B10: Admin Authentication | C10: Admin Logout & complete session destruction | D10: High | E10: Admin is logged in on dashboard. | F10: 1. Click the Logout icon button in top navigation bar. 2. Confirm the logout alert prompt ('Sign out of Vortex Admin?'). | G10: User confirmation: Yes | H10: Session cookie is destroyed, PHP session unset. Redirected to /vortex/admin/login.php?logged_out=1. Success banner displays: 'You have been securely logged out.'. Back button does not reveal authenticated pages. | I10: Not Run
A11: TC-RBAC-01 | B11: RBAC & Permissions | C11: Super Administrator full privileges verification | D11: Critical | E11: Logged in as Super Admin (`admin`). | F11: 1. Verify topbar displays '⚡ SUPER ADMIN' badge. 2. Check sidebar items: Overview, Global Search, Transactions, API Clients, Events, Admin Profile, Notifications, Audit Trail, Merchant Portal. 3. Verify 'New Event' button is visible in sidebar. | G11: Role: Super Administrator | H11: All menu items, creation buttons, refund action buttons, client onboarding wizard, and audit trail are fully accessible without restriction. | I11: Not Run
A12: TC-RBAC-02 | B12: RBAC & Permissions | C12: Operations Admin role restrictions (No Refund, No Audit) | D12: High | E12: Operations Admin account created in database (`role = 'Operations Admin'`). | F12: 1. Sign in as Operations Admin. 2. Verify sidebar shows: Events, API Clients, Overview, Transactions. 3. Verify Audit Trail link is HIDDEN. 4. Open transaction details page and check if 'Process Refund' button is HIDDEN. | G12: Role: Operations Admin | H12: Operations Admin can manage events and clients, but CANNOT see the Audit Trail or issue payment refunds. Direct URL access to audit_logs.php is forbidden. | I12: Not Run
A13: TC-RBAC-03 | B13: RBAC & Permissions | C13: Finance Officer role restrictions (Refunds allowed, No Event creation) | D13: High | E13: Finance Officer account created (`role = 'Finance Officer'`). | F13: 1. Sign in as Finance Officer. 2. Check sidebar: 'New Event' button is HIDDEN. 3. Navigate to Transactions list and open a settled payment. 4. Verify 'Process Refund' button is VISIBLE and functional. | G13: Role: Finance Officer | H13: Finance Officer has full financial permissions (view transactions, issue refunds), but event and API client creation are restricted. | I13: Not Run
A14: TC-RBAC-04 | B14: RBAC & Permissions | C14: Support Auditor read-only role enforcement | D14: Medium | E14: Support Auditor account created (`role = 'Support Auditor'`). | F14: 1. Sign in as Support Auditor. 2. Verify all action buttons (New Event, Add Client, Process Refund, Edit) are hidden. 3. Verify Audit Trail and Transactions are read-only. | G14: Role: Support Auditor | H14: System permits read-only access. Any attempt to POST modifications returns HTTP 403 / Access Denied. | I14: Not Run
A15: TC-THEME-01 | B15: Google Dark Mode | C15: Topbar Theme Toggle instant switch (Light <-> Dark) | D15: High | E15: Logged in to admin dashboard in Light mode. | F15: 1. Locate theme toggle button (sun/moon icon) in topbar. 2. Click the toggle button. 3. Observe background, topbar, sidebar, and cards. 4. Click toggle button again. | G15: Click #themeToggleBtn | H15: On first click: [data-theme='dark'] is applied instantly. Canvas turns to Google Dark #202124, surface turns to #292a2d, elevated cards to #303134. Sun icon is displayed. On second click: reverts to Light mode cleanly. | I15: Not Run
A16: TC-THEME-02 | B16: Google Dark Mode | C16: Anti-FOUC (Flash of Unstyled Content) test on reload | D16: Medium | E16: Admin set to Dark mode. | F16: 1. Set theme to Dark mode. 2. Perform a hard page reload (Ctrl+Shift+R / Cmd+Shift+R). 3. Observe page render behavior. | G16: Theme: Dark, Hard refresh | H16: Immediate flash-free render: Dark mode is applied before DOM paint via synchronous head script. No blinding white flash occurs during page load. | I16: Not Run
... A83: TC-WHQ-07 | B83: Webhook Retry Queue | C83: CLI / Cron queue worker execution (process_webhook_queue.php) | D83: Medium | E83: Terminal access to project root. | F83: 1. Run command: php vortex/tools/process_webhook_queue.php --limit=20. 2. Observe standard output metrics. | G83: CLI command execution | H83: Worker prints clean execution banner with timestamp, Scanned Due Items count, Delivered count, Rescheduled count, and latency in milliseconds. Exit code is 0. | I83: Not Run

Sheet Feature & Role Matrix
A1: VORTEX ARCHITECTURE & FEATURE COVERAGE MATRIX
A3: Module / Subsystem | B3: Primary File / Route | C3: Target Roles / Actors | D3: Automated Suite | E3: Manual QA Status | F3: Core Capabilities & Security Guards
A4: Admin Authentication | B4: /vortex/admin/login.php | C4: Super Admin, Ops, Finance, Auditor | D4: test_authentication.php | E4: Required | F4: Session regeneration, timing-safe bcrypt verify, brute force deterrence, auto-redirect
A5: RBAC Engine | B5: /vortex/classes/RBAC.php | C5: All Admin Roles | D5: test_rbac.php | E5: Required | F5: Granular capability checks (events, payments, clients, audit), dynamic role badges, permission guards
A6: Google Dark Mode | B6: /vortex/admin/assets/css/admin.css | C6: All Users & Public | D6: test_dark_mode.php | E6: Required | F6: Google Drive palette (#202124), instant anti-FOUC script, borderless cards, cookie/localStorage sync
A7: Notification Center | B7: /vortex/admin/notifications.php | C7: Admins | D7: test_notification_center.php | E7: Required | F7: Failed webhooks, dispute alerts, high-value txn flags (>₹10k), real-time unread badges, mark-read API
A8: Global Omnisearch | B8: /vortex/admin/search.php | C8: Admins | D8: test_global_search.php | E8: Required | F8: Omnisearch dropdown, '/' shortcut, multi-entity search (txns, clients, events, emails, Razorpay IDs)
A9: Merchant Onboarding | B9: /vortex/admin/api_clients/onboarding.php | C9: Super Admin, Ops Admin | D9: test_client_onboarding.php | E9: Required | F9: 4-step wizard, dual key generator (Live/Test), webhook ping diagnostic, email/SMS preference setup
A10: Transactions & Refunds | B10: /vortex/admin/payments/list_payments.php | C10: Super Admin, Finance Officer | D10: test_payment.php, test_refund.php | E10: Required | F10: Full & partial refunds, fee calculation, Razorpay refund API dispatch, reason tracking, customer alerts
A11: Merchant Portal | B11: /vortex/portal/dashboard.php | C11: API Clients / Merchants | D11: test_portal.php | E11: Required | F11: Self-service analytics, reveal/copy API credentials, secret regeneration, webhook config, CSV exports
A12: Audit Trail | B12: /vortex/admin/audit_logs.php | C12: Super Admin, Support Auditor | D12: test_audit_logger.php | E12: Required | F12: Tamper-evident logs, actor tracking, IP & User-Agent, before/after JSON diffs, sensitive key masking
A13: Conference Engine | B13: /registration.html, /registration.php | C13: Delegates, Students, Authors | D13: test_checkout_session.php | E13: Required | F13: Category fee calculations, participant intake, Vortex gateway handoff, Razorpay checkout, receipts
A14: Events Management | B14: /vortex/admin/events/index.php | C14: Super Admin, Ops Admin | D14: test_event.php | E14: Required | F14: Modal event creation, active/inactive lifecycle, multi-event routing, department revenue aggregation
A15: Webhook Retry Queue | B15: /vortex/classes/WebhookQueueService.php | C15: System Background, Admin, Merchant | D15: test_webhook_queue.php | E15: Required | F15: Exponential backoff (3, 9, 27 min), atomic row claiming, HMAC signing, CLI worker, permanent failure alerts

Sheet Defect Log
A1: VORTEX QA DEFECT LOG & BUG TRACKING SHEET
A3: Bug ID | B3: Related Test ID | C3: Defect Summary / Title | D3: Severity | E3: Steps to Reproduce | F3: Expected Behavior | G3: Observed Behavior | H3: Browser / OS | I3: Defect Status | J3: Assigned Developer Notes
A4: BUG-001 (Resolved) | B4: TC-NOTIF-01 | C4: Topbar action wrapper missing causing topbar items misalignment | D4: Major | E4: 1. Open admin dashboard in browser. 2. Observe topbar actions flexbox alignment. | F4: Topbar items aligned horizontally in a flex container on right. | G4: Missing <div class='topbar-actions'> caused topbar items to stretch across header. | H4: Chrome 129 / Linux | I4: Closed | J4: Fixed in header.php by restoring topbar-actions wrapper.
A5: BUG-002 (Resolved) | B5: TC-THEME-06 | C5: CSS warning on -webkit-line-clamp without standard line-clamp | D5: Minor | E5: 1. Inspect admin.css line 556 in editor diagnostics. | F5: Zero CSS diagnostics or vendor prefix warnings. | G5: Warning flagged: 'Also define standard property line-clamp for compatibility'. | H5: VS Code CSS Language Service | I5: Closed | J5: Added standard 'line-clamp: 2;' alongside -webkit-line-clamp in admin.css.
